setup.py
emarsys/__init__.py
emarsys/api.py
python_emarsys.egg-info/PKG-INFO
python_emarsys.egg-info/SOURCES.txt
python_emarsys.egg-info/dependency_links.txt
python_emarsys.egg-info/requires.txt
python_emarsys.egg-info/top_level.txt
python_emarsys.egg-info/zip-safe