Metadata-Version: 1.1
Name: python-emarsys
Version: 0.1
Summary: Emarsys REST API wrapper for Python.
Home-page: https://github.com/eugene-wee/python-emarsys
Author: Eugene Wee
Author-email: UNKNOWN
License: UNKNOWN
Download-URL: https://github.com/eugene-wee/python-emarsys/tarball/master
Keywords: emarsys api wrapper
Platform: UNKNOWN
Classifier: Development Status :: 2 - Pre-Alpha
Classifier: Intended Audience :: Developers
Classifier: License :: OSI Approved :: Apache Software License
Classifier: Natural Language :: English
Classifier: Operating System :: OS Independent
Classifier: Programming Language :: Python
Classifier: Topic :: Software Development :: Libraries :: Python Modules
